deepclean/__init__.py
deepclean/__main__.py
deepclean-0.1.2.dist-info/LICENSE.txt
deepclean-0.1.2.dist-info/METADATA
deepclean-0.1.2.dist-info/WHEEL
deepclean-0.1.2.dist-info/entry_points.txt
deepclean-0.1.2.dist-info/top_level.txt
deepclean-0.1.2.dist-info/RECORD
