Metadata-Version: 2.1
Name: deepclean
Version: 0.1.2
Summary: Clean old versions of Docker images.
Home-page: https://git.shore.co.il/nimrod/deepclean
Author: Nimrod Adar
Author-email: nimrod@shore.co.il
License: MIT
Keywords: docker
Platform: UNKNOWN
Classifier: Development Status :: 3 - Alpha
Classifier: Environment :: Console
Classifier: Intended Audience :: Information Technology
Classifier: Intended Audience :: System Administrators
Classifier: License :: OSI Approved :: MIT License
Classifier: Operating System :: POSIX :: Linux
Classifier: Programming Language :: Python :: 3
Classifier: Programming Language :: Python :: 3 :: Only
Classifier: Programming Language :: Python :: 3.6
Classifier: Programming Language :: Python :: 3.7
Classifier: Programming Language :: Python :: 3.8
Classifier: Programming Language :: Python :: 3.9
Classifier: Programming Language :: Python :: 3.10
Classifier: Topic :: System :: Systems Administration
Classifier: Topic :: Utilities
License-File: LICENSE.txt
Requires-Dist: docker
